python_artmap/__init__.py
python_artmap/python_artmap.py
python_artmap/art/__init__.py
python_artmap/art/art.py
python_artmap/art_fuzzy/__init__.py
python_artmap/art_fuzzy/art_fuzzy.py
python_artmap/artmap_fuzzy/__init__.py
python_artmap/artmap_fuzzy/artmap_fuzzy.py
python_artmap-0.3.0.dist-info/AUTHORS.rst
python_artmap-0.3.0.dist-info/LICENSE
python_artmap-0.3.0.dist-info/METADATA
python_artmap-0.3.0.dist-info/WHEEL
python_artmap-0.3.0.dist-info/top_level.txt
python_artmap-0.3.0.dist-info/RECORD
