Metadata-Version: 2.1
Name: python-artmap
Version: 0.3.0
Summary: A Python Library of Neural network ARTMAP
Home-page: https://github.com/DavidVinicius/python_artmap
Author: David Vinicius
Author-email: de.175@hotmail.com
License: MIT license
Keywords: python_artmap
Platform: UNKNOWN
Classifier: Development Status :: 2 - Pre-Alpha
Classifier: Intended Audience :: Developers
Classifier: License :: OSI Approved :: MIT License
Classifier: Natural Language :: English
Classifier: Programming Language :: Python :: 3
Classifier: Programming Language :: Python :: 3.5
Classifier: Programming Language :: Python :: 3.6
Classifier: Programming Language :: Python :: 3.7
Classifier: Programming Language :: Python :: 3.8
Requires-Python: >=3.5
Requires-Dist: numpy
